terminal_agent/__init__.py
terminal_agent/agent.py
terminal_agent-0.1.3.dist-info/METADATA
terminal_agent-0.1.3.dist-info/WHEEL
terminal_agent-0.1.3.dist-info/entry_points.txt
terminal_agent-0.1.3.dist-info/top_level.txt
terminal_agent-0.1.3.dist-info/RECORD
